{
    "info": {
        "code": "mh",
        "name": "漫画",
        "cat_num": 52
    },
    "data": [
        {
            "des": "Kindle，合集,日漫",
            "title": "Kindle 漫画书合集",
            "tok": "",
            "cat": "mh",
            "key": "B4DMQP6LV7BT5AXP24MZZS2S7REJN5LD5PTZGDMIHITYAQRCQPZ7OA"
        },
        {
            "des": "很多小孩子看得绘本，类似书本一样的PDF文档，按类别分类的，比较多的",
            "title": "儿童绘本电子书PDF",
            "tok": "",
            "cat": "mh",
            "key": "B3AO3CZZP35QDMWCDB3AXEEKQFN4FIMKM3MRJCOEIJWZHUB3IWMGZNQ"
        },
        {
            "des": "MT韩漫大合集一共有436本",
            "title": "MT韩漫大合集",
            "tok": "",
            "cat": "mh",
            "key": "B3AJNZPCCQJISVHT6ZL2S36L3HJNVWZPF27ANURW2UDTJPLSZEOBMYC"
        },
        {
            "des": "",
            "title": "龍珠1-34 卷",
            "tok": "",
            "cat": "mh",
            "key": "B3ALJRBWVNDOKQZFVF7KR6SAFPXA475TD76TW6J6EQFANAJ57B7GHHY"
        },
        {
            "des": "",
            "title": "春輝漫画",
            "tok": "",
            "cat": "mh",
            "key": "B2T4TONEYLKO5OLYZG4MEBNOHRLQLXBHKSIQKUWN3PUJSWIGGATHECWKAU"
        }
    ]
}